async_mail/__init__.py
async_mail/config.py
async_mail/errors.py
async_mail/models.py
async_mail/backends/__init__.py
async_mail/backends/base.py
async_mail/backends/smtp.py
async_mail-0.1b0.dist-info/DESCRIPTION.rst
async_mail-0.1b0.dist-info/METADATA
async_mail-0.1b0.dist-info/RECORD
async_mail-0.1b0.dist-info/WHEEL
async_mail-0.1b0.dist-info/metadata.json
async_mail-0.1b0.dist-info/top_level.txt
