Metadata-Version: 2.0
Name: async-mail
Version: 0.1b0
Summary: async mail with simple settings and django settings support.
Home-page: https://github.com/larsclaussen/async_mail
Author: Lars Claussen
Author-email: claussen.lars@nelen-schuurmans.nl
License: MIT license
Keywords: async_mail
Platform: UNKNOWN
Classifier: Development Status :: 2 - Pre-Alpha
Classifier: Intended Audience :: Developers
Classifier: License :: OSI Approved :: MIT License
Classifier: Natural Language :: English
Classifier: Programming Language :: Python :: 3
Classifier: Programming Language :: Python :: 3.7
Classifier: Programming Language :: Python :: 3.8
Requires-Python: >=3.7
Requires-Dist: aiosmtplib (>=1.1.3)
Requires-Dist: pydantic (>=1.5.1)
